Workbook

Sheet 00_How_to_use
A1: Arda Link — Mom Test tracker
A3: Mom Test field tracker — where the 10 interviews become rows, and a verdict.
A5: 1. 01_Screener: book the interviews (screening facts + which quota each one fills).
A6: 2. 02_Hypotheses: after each interview mark Y / N / ? for every hypothesis id, and record the evidence id from 04_Quotes.
A7: 3. 03_Interview_Log: one row per visit, including the product-test outcomes (T1-T8).
A8: 4. 04_Quotes: verbatim quotes only, each tagged and tied to a hypothesis.
A9: 5. 05_Numbers: every number he gave - minimum three per interview.
A10: 6. 06_WhoIsWho: complete the user / beneficiary / payer / gatekeeper map.
A11: 7. 07_Gate: fills itself from the other sheets. Read the verdict before deciding what to build next.
A13: Rule of the whole round: unprompted mentions count, prompted agreement does not. Numbers or it did not happen. The script is docs/field/mom_test_field_kit.md (section 4) - and never pitch.

Sheet 01_Screener
A1: # | B1: Initials | C1: Sex | D1: Age band | E1: Ward | F1: Water point | G1: Walk time (min) | H1: Distance band | I1: Species | J1: Herd size | K1: Who holds the phone | L1: WhatsApp (Y/N) | M1: Reads / listens | N1: Shares phone (Y/N) | O1: Bad health event (Y/N) | P1: Quota filled | Q1: Interviewer | R1: Date booked | S1: Status
A2: 1
A3: 2
A4: 3
A5: 4
A6: 5
A7: 6
A8: 7
A9: 8
A10: 9
A11: 10
A12: 11
A13: 12
... A16: 15

Sheet 02_Hypotheses
A1: ID | B1: Hypothesis | C1: TRUE if | D1: FALSE -> kill/pivot | E1: T | F1: How tested | G1: I01 | H1: I02 | I1: I03 | J1: I04 | K1: I05 | L1: I06 | M1: I07 | N1: I08 | O1: I09 | P1: I10 | Q1: I11 | R1: I12 | S1: I13 | T1: I14 | U1: I15 | V1: Y count | W1: N count | X1: Verdict
A2: D1 | B2: The water and grazing decision is frequent, hard and expensive | C2: >=6/10 describe a specific episode with a month, a place and a cost | D2: <4/10 describe any specific loss | E2: 6 | F2: B4-B9, C10-C15, D16-D21 | U2: =COUNTIF(F2:T2,"Y") | V2: =COUNTIF(F2:T2,"N") | W2: =IF(U2+V2=0,"",IF(U2>=E2,"SUPPORTED",IF(V2>=16-E2,"CONTRADICTED","UNKNOWN")))
A3: D2 | B3: Information is the binding constraint, not money, water or land | C3: They pay or travel to find out, and act on what they learn | D3: They know and still cannot act | E3: 6 | F3: C11-C12, E23-E26, H38 | U3: =COUNTIF(F3:T3,"Y") | V3: =COUNTIF(F3:T3,"N") | W3: =IF(U3+V3=0,"",IF(U3>=E3,"SUPPORTED",IF(V3>=16-E3,"CONTRADICTED","UNKNOWN")))
A4: D3 | B4: The loss is big enough to matter to a household | C4: Named losses in animals, milk or shillings in the last 12 months | D4: Losses are rare and small | E4: 6 | F4: D19, H37, K51 | U4: =COUNTIF(F4:T4,"Y") | V4: =COUNTIF(F4:T4,"N") | W4: =IF(U4+V4=0,"",IF(U4>=E4,"SUPPORTED",IF(V4>=16-E4,"CONTRADICTED","UNKNOWN")))
A5: D4 | B5: It is a recurring decision, not once a year | C5: Weekly-to-monthly cadence in >=6/10 | D5: Once a season | E5: 6 | F5: B4, C10, D16 | U5: =COUNTIF(F5:T5,"Y") | V5: =COUNTIF(F5:T5,"N") | W5: =IF(U5+V5=0,"",IF(U5>=E5,"SUPPORTED",IF(V5>=16-E5,"CONTRADICTED","UNKNOWN")))
A6: U1 | B6: A herder can find and use a WhatsApp service without training | C6: >=7/10 complete the task unaided | D6: <=4/10 complete the task | E6: 7 | F6: T1, T3, G36 | U6: =COUNTIF(F6:T6,"Y") | V6: =COUNTIF(F6:T6,"N") | W6: =IF(U6+V6=0,"",IF(U6>=E6,"SUPPORTED",IF(V6>=16-E6,"CONTRADICTED","UNKNOWN")))
A7: U2 | B7: One tap is a price he will pay to receive something | C7: >=6/10 report once, or agree to a test | D7: Most refuse | E7: 6 | F7: T3, M57 | U7: =COUNTIF(F7:T7,"Y") | V7: =COUNTIF(F7:T7,"N") | W7: =IF(U7+V7=0,"",IF(U7>=E7,"SUPPORTED",IF(V7>=16-E7,"CONTRADICTED","UNKNOWN")))
A8: U3 | B8: Voice beats text for the people who matter most | C8: Voice chosen by the least literate and the most remote | D8: Text dominates | E8: 6 | F8: T4, G35 | U8: =COUNTIF(F8:T8,"Y") | V8: =COUNTIF(F8:T8,"N") | W8: =IF(U8+V8=0,"",IF(U8>=E8,"SUPPORTED",IF(V8>=16-E8,"CONTRADICTED","UNKNOWN")))
A9: U4 | B9: Our messages are understood the first time | C9: >=8/10 restate the advice correctly | D9: Common misreadings | E9: 8 | F9: T2 | U9: =COUNTIF(F9:T9,"Y") | V9: =COUNTIF(F9:T9,"N") | W9: =IF(U9+V9=0,"",IF(U9>=E9,"SUPPORTED",IF(V9>=16-E9,"CONTRADICTED","UNKNOWN")))
A10: F1 | B10: A kg estimate is credible and useful | C10: A reference weight exists and a use is named | D10: No reference weights anywhere | E10: 6 | F10: T6 | U10: =COUNTIF(F10:T10,"Y") | V10: =COUNTIF(F10:T10,"N") | W10: =IF(U10+V10=0,"",IF(U10>=E10,"SUPPORTED",IF(V10>=16-E10,"CONTRADICTED","UNKNOWN")))
A11: F2 | B11: Rain-onset language survives being wrong | C11: He tolerates estimate wording and keeps using it | D11: He punishes any miss | E11: 6 | F11: T7, I42 | U11: =COUNTIF(F11:T11,"Y") | V11: =COUNTIF(F11:T11,"N") | W11: =IF(U11+V11=0,"",IF(U11>=E11,"SUPPORTED",IF(V11>=16-E11,"CONTRADICTED","UNKNOWN")))
A12: F3 | B12: The map is readable and its age is understood | C12: He finds his place and reads the date / kadirio | D12: He reads the map as today | E12: 6 | F12: T5 | U12: =COUNTIF(F12:T12,"Y") | V12: =COUNTIF(F12:T12,"N") | W12: =IF(U12+V12=0,"",IF(U12>=E12,"SUPPORTED",IF(V12>=16-E12,"CONTRADICTED","UNKNOWN")))
A13: S1 | B13: He already passes information on, or will | C13: >=6/10 describe a specific time they passed on water or pest news | D13: Nobody has ever reported anything to anyone | E13: 6 | F13: L52-L55 | U13: =COUNTIF(F13:T13,"Y") | V13: =COUNTIF(F13:T13,"N") | W13: =IF(U13+V13=0,"",IF(U13>=E13,"SUPPORTED",IF(V13>=16-E13,"CONTRADICTED","UNKNOWN")))
... A26: A4 | B26: We can reach him without an NGO or the county | C26: — | D26: Distribution needs a gatekeeper we do not have | E26: 6 | F26: informants, M58 | U26: =COUNTIF(F26:T26,"Y") | V26: =COUNTIF(F26:T26,"N") | W26: =IF(U26+V26=0,"",IF(U26>=E26,"SUPPORTED",IF(V26>=16-E26,"CONTRADICTED","UNKNOWN")))

Sheet 03_Interview_Log
A1: # | B1: Date | C1: Place | D1: Ward | E1: Start | F1: End | G1: Minutes | H1: Consent (Y/N) | I1: Recorder (Y/N) | J1: Who present | K1: T1 unaided find | L1: T2 misreadings | M1: T3 one-tap report | N1: T4 voice / text | O1: T5 map verdict | P1: T6 reference weight | Q1: T7 uncertainty | R1: T8 forward path | S1: Callback agreed (Y/N) | T1: Introduction given (Y/N) | U1: Test agreed (Y/N) | V1: My one line tonight
A2: 1
A3: 2
A4: 3
A5: 4
A6: 5
A7: 6
A8: 7
A9: 8
A10: 9
A11: 10
A12: 11
A13: 12
... A16: 15

Sheet 04_Quotes
A1: # | B1: Interview # | C1: Section | D1: Tag | E1: Quote (verbatim) | F1: Translation (if not English/Swahili) | G1: Hypothesis id

Sheet 05_Numbers
A1: Interview # | B1: Item | C1: Value | D1: Unit | E1: Question # | F1: Hyp id | G1: Tag

Sheet 06_WhoIsWho
A1: Role | B1: Who (real name) | C1: Ward | D1: What they want | E1: What it costs them today | F1: Gives (data) | G1: Pays? | H1: Contact | I1: Next step | J1: Owner | K1: Date
A2: Herder / owner — user, decision maker | D2: Not to lose animals; know where to move | E2: Wasted walks, dead animals, milk drop | F2: One-tap report from the point | G2: Never pays
A3: Young herder — user, daily with the animals | D3: Water today, no wasted walking | E3: Hours, km, heat | F3: The most reports, most often | G3: Never pays
A4: Woman in the manyatta — user + beneficiary | D4: Milk, children's food, water, milk price | E4: Walks to water, milk loss, sick shoats | F4: Queue and shoats observations | G4: Never pays
A5: Household / children / elderly — beneficiary | D5: Food, milk, income stability | E5: Nutrition when herds fail | F5: Nothing — he is why the herder never pays | G5: Never pays
A6: Water point committee / WRUA — gatekeeper | D6: A working point, no fights | E6: Queue conflict, breakdowns | F6: Confirms repairs, validates reports | G6: No (may hold a fund)
A7: Agrovet — channel + trust anchor | D7: Footfall, correct drug use | E7: Wrong products bought, no follow-up | F7: Distribution; pest observations at the counter | G7: Maybe — footfall/stock data
A8: County livestock / water dept — BUYER | D8: Surveillance, service delivery, fewer outbreaks | E8: Collecting ward ground truth by vehicle and phone | F8: Nothing (or it reviews our wording) | G8: YES — county budget line
A9: NDMA ward officer — BUYER / data partner | D9: Timely ward ground truth on water and pasture | E9: Fuel, staff time, late reports | F9: Nothing (it is a consumer) | G9: YES — monitoring / early-warning line
A10: NGO / CBO project — BUYER (M&E) | D10: Reach, evidence for funders | E10: Expensive last-mile data collection | F10: Distribution and field access | G10: YES — per ward per month
A11: Insurer / research institute — buyer, later | D11: Underwriting data; longitudinal herd data | E11: Sample surveys, scarce baselines | F11: Nothing | G11: Later — needs 6+ months of records
A12: Chief / ward admin — distribution | D12: Order, service, being seen to help | E12: Nothing | F12: Baraza announcement, signboard | G12: No

Sheet 07_Gate
A1: Decision gate — read this before deciding what to build next
A3: Metric | B3: Value | C3: Threshold | D3: Where it comes from
A4: Interviews completed (10 pastoralists + 5 informants) | B4: =COUNTA('03_Interview_Log'!A2:A16) | C4: 15 | D4: 03_Interview_Log
A5: A specific costly decision described (D1) | B5: ='02_Hypotheses'!U2 | C5: >=6 | D5: hypothesis D1
A6: He already reports, or agrees to (S1) | B6: ='02_Hypotheses'!U13 | C6: >=6 | D6: hypothesis S1
A7: One tap completed unaided or accepted (S2) | B7: ='02_Hypotheses'!U14 | C7: >=6 | D7: hypothesis S2
A8: His reports are good enough to sell (S3) | B8: ='02_Hypotheses'!U15 | C8: >=6 | D8: hypothesis S3
A9: A buyer with a real current spend (V1) | B9: ='02_Hypotheses'!U17 | C9: >=1 | D9: hypothesis V1 - informant interviews
A10: A budget line, owner and cycle (V2) | B10: ='02_Hypotheses'!U18 | C10: >=1 | D10: hypothesis V2 - informant interviews
A11: Commitments accepted (callback / intro / test) | B11: =COUNTIF('03_Interview_Log'!S2:U16,"Y") | C11: >=4 | D11: Appendix M / section 4 close
A13: VERDICT | B13: =IF(B4<10,"NOT ENOUGH INTERVIEWS YET",IF(B5<4,"REFRAME / STOP - fewer than 4 of 10 can describe a specific, costly decision",IF(AND(B5>=6,B6>=6,B7>=6,B9>=1,B10>=1,B11>=4),"GO - the problem, the supply habit, the buyer and the commitments all clear the bar",IF(B9<1,"NO BUYER YET - the service may be real, but no institution currently pays to collect this data: re-read section 8 before building more","PIVOT - the problem or the buyer is there but the supply or the segment is wrong: re-read section 8"))))
A15: Problem clustering (one row per problem; unprompted mentions only)
A16: Problem (in their words) | B16: Unprompted /10 | C16: Cost today (their numbers) | D16: What they do now | E16: Does our product address it? | F16: Verdict
A24: Decisions log
A25: Decision | B25: Evidence (interview #, quote or number) | C25: Owner | D25: By when
